<?xml version="1.0" encoding="UTF-8"?>
<!-- Created with TexturePacker http://texturepacker.com-->
<!-- $TexturePacker:SmartUpdate:f14f7776bcbb3fdc3799b66b1529ce27$ -->
<TextureAtlas imagePath="dok.png">
    <SubTexture name="Img_PODD" x="2" y="2" width="1024" height="329"/>
    <SubTexture name="O" x="1028" y="2" width="337" height="329"/>
    <SubTexture name="btn_Backs" x="1367" y="2" width="50" height="50"/>
    <SubTexture name="btn_Button" x="1419" y="2" width="378" height="58"/>
    <SubTexture name="btn_No" x="1799" y="2" width="48" height="34"/>
    <SubTexture name="btn_Pause" x="1849" y="2" width="50" height="50"/>
    <SubTexture name="btn_Play" x="1901" y="2" width="50" height="50"/>
    <SubTexture name="btn_Yes" x="1953" y="2" width="55" height="34"/>
    <SubTexture name="btn_back" x="2" y="333" width="89" height="75"/>
    <SubTexture name="btn_back" x="2" y="333" width="89" height="75"/>
    <SubTexture name="btn_next" x="93" y="333" width="89" height="75"/>
    <SubTexture name="img_Coin" x="184" y="333" width="36" height="35"/>
    <SubTexture name="img_Quality" x="222" y="333" width="159" height="56"/>
    <SubTexture name="img_Scroll" x="383" y="333" width="762" height="726" frameX="-139" frameY="-15" frameWidth="1024" frameHeight="768"/>
    <SubTexture name="img_Title" x="1147" y="333" width="370" height="288"/>
    <SubTexture name="img_Volume" x="1519" y="333" width="185" height="50"/>
</TextureAtlas>
